kafka_influxdb/__init__.py
kafka_influxdb/__main__.py
kafka_influxdb/version.py
kafka_influxdb/worker.py
kafka_influxdb/config/__init__.py
kafka_influxdb/config/default_config.py
kafka_influxdb/config/loader.py
kafka_influxdb/encoder/__init__.py
kafka_influxdb/encoder/collectd_graphite_encoder.py
kafka_influxdb/encoder/collectd_json_encoder.py
kafka_influxdb/encoder/echo_encoder.py
kafka_influxdb/encoder/errors.py
kafka_influxdb/encoder/escape_functions.py
kafka_influxdb/encoder/graphite_encoder.py
kafka_influxdb/encoder/heapster_event_json_encoder.py
kafka_influxdb/encoder/heapster_json_encoder.py
kafka_influxdb/reader/__init__.py
kafka_influxdb/reader/confluent.py
kafka_influxdb/reader/kafka_python.py
kafka_influxdb/reader/kafka_reader.py
kafka_influxdb/reader/reader.py
kafka_influxdb/template/__init__.py
kafka_influxdb/template/graphite.py
kafka_influxdb/tests/__init__.py
kafka_influxdb/tests/test_worker.py
kafka_influxdb/tests/encoder_test/__init__.py
kafka_influxdb/tests/encoder_test/test_collectd_graphite_encoder.py
kafka_influxdb/tests/encoder_test/test_collectd_json_encoder.py
kafka_influxdb/tests/encoder_test/test_echo_encoder.py
kafka_influxdb/tests/encoder_test/test_graphite_encoder.py
kafka_influxdb/tests/encoder_test/test_heapster_event_json_encoder.py
kafka_influxdb/tests/encoder_test/test_heapster_json_encoder.py
kafka_influxdb/tests/helpers/__init__.py
kafka_influxdb/tests/helpers/timeout.py
kafka_influxdb/tests/reader_test/__init__.py
kafka_influxdb/tests/reader_test/test_confluent.py
kafka_influxdb/tests/reader_test/test_kafka_python.py
kafka_influxdb/tests/reader_test/test_kafka_reader.py
kafka_influxdb/tests/writer_test/__init__.py
kafka_influxdb/tests/writer_test/test_influxdb_writer.py
kafka_influxdb/writer/__init__.py
kafka_influxdb/writer/influxdb_writer.py
kafka_influxdb/writer/kafka_sample_writer.py
kafka_influxdb-0.9.3.dist-info/DESCRIPTION.rst
kafka_influxdb-0.9.3.dist-info/METADATA
kafka_influxdb-0.9.3.dist-info/RECORD
kafka_influxdb-0.9.3.dist-info/WHEEL
kafka_influxdb-0.9.3.dist-info/entry_points.txt
kafka_influxdb-0.9.3.dist-info/metadata.json
kafka_influxdb-0.9.3.dist-info/pbr.json
kafka_influxdb-0.9.3.dist-info/top_level.txt
