Metadata-Version: 2.0
Name: kafka-influxdb
Version: 0.9.3
Summary: A Kafka consumer for InfluxDB
Home-page: http://github.com/mre/kafka-influxdb
Author: Matthias Endler
Author-email: matthias-endler@gmx.net
License: Apache
Keywords: kafka influxdb metrics consumer
Platform: UNKNOWN
Classifier: Development Status :: 4 - Beta
Classifier: License :: OSI Approved :: Apache Software License
Classifier: Topic :: Utilities
Classifier: Programming Language :: Python
Classifier: Programming Language :: Python :: 2
Classifier: Programming Language :: Python :: 2.7
Classifier: Programming Language :: Python :: 3
Classifier: Programming Language :: Python :: 3.3
Classifier: Programming Language :: Python :: 3.4
Classifier: Programming Language :: Python :: 3.5
Classifier: Programming Language :: Python :: 3.6
Classifier: Programming Language :: Python :: Implementation :: PyPy
Requires-Dist: PyYAML
Requires-Dist: certifi
Requires-Dist: confluent-kafka
Requires-Dist: funcsigs
Requires-Dist: influxdb
Requires-Dist: kafka-python
Requires-Dist: pbr
Requires-Dist: pytest-runner
Requires-Dist: python-dateutil
Requires-Dist: pytz
Requires-Dist: requests
Requires-Dist: six
Requires-Dist: ujson
Requires-Dist: virtualenv
Requires-Dist: wheel
